titantic_classification/VERSION
titantic_classification/__init__.py
titantic_classification/pipeline.py
titantic_classification/predict.py
titantic_classification/train_pipeline.py
titantic_classification/config/__init__.py
titantic_classification/config/core.py
titantic_classification/datasets/__init__.py
titantic_classification/processing/__init__.py
titantic_classification/processing/data_manager.py
titantic_classification/processing/features.py
titantic_classification/processing/validation.py
titantic_classification/trained_models/__init__.py
titantic_classification_model_aa-0.0.5.dist-info/METADATA
titantic_classification_model_aa-0.0.5.dist-info/WHEEL
titantic_classification_model_aa-0.0.5.dist-info/top_level.txt
titantic_classification_model_aa-0.0.5.dist-info/RECORD
